{
  "_comment": "REVIEWS DATABASE - Edit this file to manage reviews",
  "_instructions": {
    "how_to_add_position": "Change 'position': null to 'position': 'Coach at Blau Weiss Berlin'",
    "how_to_add_photo": "Change 'photo': null to 'photo': 'https://your-cloudinary-url.jpg'",
    "how_to_feature": "Change 'featured': false to 'featured': true (review will appear in carousel)",
    "how_to_delete": "Delete the entire review object from the array",
    "featured_reviews": "Only reviews with 'featured': true appear in the carousel at top of page",
    "all_reviews": "All reviews appear in the grid below carousel, newest first"
  },
  "reviews": [
    {
      "id": "1766384762260",
      "name": "Anonymous",
      "position": null,
      "photo": null,
      "rating": 5,
      "text": "Great photographer, been an absolute blast working with him. Really great at communication and keeps the shoot fun and friendly.",
      "date": "2025-10-22",
      "featured": false
    },
    {
      "id": "1766390664375",
      "name": "Divyansh Chawla",
      "position": null,
      "photo": null,
      "rating": 5,
      "text": "Arpith is a great photographer with an outstanding editing skills. He can capture rare moments like no one I know of. He also clicked some of my portraits which i liked so much that i posted on instagram. I really recommend him as other than his skills, he has a great personality.",
      "date": "2025-12-22",
      "featured": false
    },
    {
      "id": "1766411969391",
      "name": "Abhishek ",
      "position": null,
      "photo": null,
      "rating": 5,
      "text": "Had a him shoot my car before he moved to Germany. Loved the results. Absolutely recommend.",
      "date": "2025-12-22",
      "featured": false
    }
  ]
}